fileupload/__init__.py
fileupload/widget.py
fileupload/static/extension.js
fileupload/static/widget.js
fileupload/static/fileupload/widget.js
fileupload-0.1.5.dist-info/DESCRIPTION.rst
fileupload-0.1.5.dist-info/METADATA
fileupload-0.1.5.dist-info/RECORD
fileupload-0.1.5.dist-info/WHEEL
fileupload-0.1.5.dist-info/metadata.json
fileupload-0.1.5.dist-info/pbr.json
fileupload-0.1.5.dist-info/top_level.txt
