Metadata-Version: 2.0
Name: fileupload
Version: 0.1.5
Summary: IPython file upload widget
Home-page: https://github.com/peteut/ipython-file-upload
Author: Alain Péteut
Author-email: alain.peteut@yahoo.com
License: MIT
Keywords: file
Requires-Dist: ipywidgets (>=5.1)
Requires-Dist: notebook (>=4.2)
Requires-Dist: traitlets (>=4.2)
